repostat/stash.py
repostat/test_stash.py
repostat-0.1.dist-info/DESCRIPTION.rst
repostat-0.1.dist-info/METADATA
repostat-0.1.dist-info/RECORD
repostat-0.1.dist-info/WHEEL
repostat-0.1.dist-info/metadata.json
repostat-0.1.dist-info/top_level.txt
